palettetown/__init__.py
palettetown/pokedex.py
palettetown/pokemon.py
palettetown/pokeplot.py
palettetown/data/__init__.py
palettetown/data/pokedex.json
palettetown/data/sprites/__init__.py
palettetown/data/sprites/abomasnow.png
palettetown/data/sprites/abra.png
palettetown/data/sprites/absol.png
palettetown/data/sprites/accelgor.png
palettetown/data/sprites/aegislash.png
palettetown/data/sprites/aerodactyl.png
palettetown/data/sprites/aggron.png
palettetown/data/sprites/aipom.png
palettetown/data/sprites/alakazam.png
palettetown/data/sprites/alcremie.png
palettetown/data/sprites/alomomola.png
palettetown/data/sprites/altaria.png
palettetown/data/sprites/amaura.png
palettetown/data/sprites/ambipom.png
palettetown/data/sprites/amoonguss.png
palettetown/data/sprites/ampharos.png
palettetown/data/sprites/anorith.png
palettetown/data/sprites/appletun.png
palettetown/data/sprites/applin.png
palettetown/data/sprites/araquanid.png
palettetown/data/sprites/arbok.png
palettetown/data/sprites/arcanine.png
palettetown/data/sprites/arceus.png
palettetown/data/sprites/archen.png
palettetown/data/sprites/archeops.png
palettetown/data/sprites/arctovish.png
palettetown/data/sprites/arctozolt.png
palettetown/data/sprites/ariados.png
palettetown/data/sprites/armaldo.png
palettetown/data/sprites/aromatisse.png
palettetown/data/sprites/aron.png
palettetown/data/sprites/arrokuda.png
palettetown/data/sprites/articuno.png
palettetown/data/sprites/audino.png
palettetown/data/sprites/aurorus.png
palettetown/data/sprites/avalugg.png
palettetown/data/sprites/axew.png
palettetown/data/sprites/azelf.png
palettetown/data/sprites/azumarill.png
palettetown/data/sprites/azurill.png
palettetown/data/sprites/bagon.png
palettetown/data/sprites/baltoy.png
palettetown/data/sprites/banette.png
palettetown/data/sprites/barbaracle.png
palettetown/data/sprites/barboach.png
palettetown/data/sprites/barraskewda.png
palettetown/data/sprites/basculin.png
palettetown/data/sprites/bastiodon.png
palettetown-1.0.3.dist-info/LICENSE
palettetown-1.0.3.dist-info/METADATA
palettetown-1.0.3.dist-info/WHEEL
palettetown-1.0.3.dist-info/top_level.txt
palettetown-1.0.3.dist-info/RECORD
