Metadata-Version: 2.1
Name: palettetown
Version: 1.0.3
Summary: Style plots with Pokemon colors
Home-page: https://github.com/rowland-208/palettetown
Author: James Rowland
Author-email: rowland.208@gmail.com
Project-URL: Bug Tracker, https://github.com/rowland-208/palettetown/issues
Classifier: License :: OSI Approved :: MIT License
Classifier: Operating System :: OS Independent
Classifier: Programming Language :: Python
Classifier: Programming Language :: Python :: 3
Classifier: Programming Language :: Python :: 3.10
Requires-Python: >=3.7
License-File: LICENSE
Requires-Dist: cycler
Requires-Dist: matplotlib
Requires-Dist: numpy
